cdktf_cdktf_provider_google/__init__.py
cdktf_cdktf_provider_google/py.typed
cdktf_cdktf_provider_google/_jsii/__init__.py
cdktf_cdktf_provider_google/_jsii/provider-google@16.12.0.jsii.tgz
cdktf_cdktf_provider_google/access_context_manager_access_level/__init__.py
cdktf_cdktf_provider_google/access_context_manager_access_level_condition/__init__.py
cdktf_cdktf_provider_google/access_context_manager_access_levels/__init__.py
cdktf_cdktf_provider_google/access_context_manager_access_policy/__init__.py
cdktf_cdktf_provider_google/access_context_manager_access_policy_iam_binding/__init__.py
cdktf_cdktf_provider_google/access_context_manager_access_policy_iam_member/__init__.py
cdktf_cdktf_provider_google/access_context_manager_access_policy_iam_policy/__init__.py
cdktf_cdktf_provider_google/access_context_manager_authorized_orgs_desc/__init__.py
cdktf_cdktf_provider_google/access_context_manager_egress_policy/__init__.py
cdktf_cdktf_provider_google/access_context_manager_gcp_user_access_binding/__init__.py
cdktf_cdktf_provider_google/access_context_manager_ingress_policy/__init__.py
cdktf_cdktf_provider_google/access_context_manager_service_perimeter/__init__.py
cdktf_cdktf_provider_google/access_context_manager_service_perimeter_dry_run_egress_policy/__init__.py
cdktf_cdktf_provider_google/access_context_manager_service_perimeter_dry_run_ingress_policy/__init__.py
cdktf_cdktf_provider_google/access_context_manager_service_perimeter_dry_run_resource/__init__.py
cdktf_cdktf_provider_google/access_context_manager_service_perimeter_egress_policy/__init__.py
cdktf_cdktf_provider_google/access_context_manager_service_perimeter_ingress_policy/__init__.py
cdktf_cdktf_provider_google/access_context_manager_service_perimeter_resource/__init__.py
cdktf_cdktf_provider_google/access_context_manager_service_perimeters/__init__.py
cdktf_cdktf_provider_google/active_directory_domain/__init__.py
cdktf_cdktf_provider_google/active_directory_domain_trust/__init__.py
cdktf_cdktf_provider_google-16.12.0.dist-info/LICENSE
cdktf_cdktf_provider_google-16.12.0.dist-info/METADATA
cdktf_cdktf_provider_google-16.12.0.dist-info/WHEEL
cdktf_cdktf_provider_google-16.12.0.dist-info/top_level.txt
cdktf_cdktf_provider_google-16.12.0.dist-info/RECORD
